[
{"cin":"AA111111", "cne":"L123456789", "nationality":"", "fullname":"John Doe", "date_birthday":"01/01/1995", "gender":"M", "address":"123 Main St", "code_postal":"12345", "phone":"123-456-7890", "email":"john@example.com", "father":"James Doe", "mather":"Jane Doe"},
{"cin":"BB222222", "cne":"M234567890", "nationality":"350", "fullname":"Jane Smith", "date_birthday":"02/14/1996", "gender":"F", "address":"456 Park Ave", "code_postal":"54321", "phone":"234-567-8901", "email":"jane@example.com", "father":"Bob Smith", "mather":"Sue Smith"},
{"cin":"CC333333", "cne":"N345678901", "nationality":"", "fullname":"Bob Johnson", "date_birthday":"03/15/1997", "gender":"M", "address":"789 Maple St", "code_postal":"67890", "phone":"345-678-9012", "email":"bob@example.com", "father":"Tom Johnson", "mather":"Emily Johnson"},
{"cin":"AA111111", "cne":"L123456789", "nationality":"", "fullname":"John Doe", "date_birthday":"01/01/1995", "gender":"M", "address":"123 Main St", "code_postal":"12345", "phone":"123-456-7890", "email":"john@example.com", "father":"James Doe", "mather":"Jane Doe"},
{"cin":"BB222222", "cne":"M234567890", "nationality":"350", "fullname":"Jane Smith", "date_birthday":"02/14/1996", "gender":"F", "address":"456 Park Ave", "code_postal":"54321", "phone":"234-567-8901", "email":"jane@example.com", "father":"Bob Smith", "mather":"Sue Smith"},
{"cin":"AA111111", "cne":"L123456789", "nationality":"", "fullname":"John Doe", "date_birthday":"01/01/1995", "gender":"M", "address":"123 Main St", "code_postal":"12345", "phone":"123-456-7890", "email":"john@example.com", "father":"James Doe", "mather":"Jane Doe"},
{"cin":"BB222222", "cne":"M234567890", "nationality":"350", "fullname":"Jane Smith", "date_birthday":"02/14/1996", "gender":"F", "address":"456 Park Ave", "code_postal":"54321", "phone":"234-567-8901", "email":"jane@example.com", "father":"Bob Smith", "mather":"Sue Smith"},
{"cin":"CC333333", "cne":"N345678901", "nationality":"", "fullname":"Bob Johnson", "date_birthday":"03/15/1997", "gender":"M", "address":"789 Maple St", "code_postal":"67890", "phone":"345-678-9012", "email":"bob@example.com", "father":"Tom Johnson", "mather":"Emily Johnson"},
{"cin":"DD444444", "cne":"O456789012", "nationality":"", "fullname":"Emily Williams", "date_birthday":"04/16/1998", "gender":"F", "address":"321 Pine St", "code_postal":"98765", "phone":"456-789-0123", "email":"emily@example.com", "father":"David Williams", "mather":"Katie Williams"},
{"cin":"EE555555", "cne":"P567890123", "nationality":"350", "fullname":"James Brown", "date_birthday":"05/17/1999", "gender":"M", "address":"654 Oak St", "code_postal":"43210", "phone":"567-890-1234", "email":"james@example.com", "father":"Mike Brown", "mather":"Sarah Brown"}
]
